tornado_mixpanel
