Metadata-Version: 1.1
Name: tornado-mixpanel
Version: 0.2
Summary: An async client for mixpanel.
Home-page: https://github.com/alejandrobernardis/tornado-mixpanel
Author: Alejandro M. Bernardis
Author-email: alejandro.m.bernardis@gmail.com
License: MIT
Platform: Linux
Classifier: Development Status :: 4 - Beta
Classifier: License :: OSI Approved :: MIT License
Classifier: Intended Audience :: Developers
Classifier: Natural Language :: English
Classifier: Natural Language :: Spanish
Classifier: Operating System :: POSIX :: Linux
Classifier: Programming Language :: Python :: 2.7
Classifier: Topic :: Internet :: WWW/HTTP
Classifier: Topic :: Software Development :: Libraries :: Application Frameworks
Classifier: Topic :: Software Development :: Libraries :: Python Modules
Classifier: Topic :: Utilities
